fontrpmspec/__init__.py
fontrpmspec/_debugpath.py
fontrpmspec/converter.py
fontrpmspec/errors.py
fontrpmspec/font_reader.py
fontrpmspec/generator.py
fontrpmspec/gentmt.py
fontrpmspec/messages.py
fontrpmspec/package.py
fontrpmspec/sources.py
fontrpmspec/template.py
fontrpmspec/template/spectemplate-fonts-multi.spec
fontrpmspec/template/spectemplate-fonts-simple.spec
fontrpmspec-0.19.dist-info/licenses/LICENSE
fontrpmspec-0.19.dist-info/METADATA
fontrpmspec-0.19.dist-info/WHEEL
fontrpmspec-0.19.dist-info/entry_points.txt
fontrpmspec-0.19.dist-info/top_level.txt
fontrpmspec-0.19.dist-info/RECORD
