Metadata-Version: 2.4
Name: fontrpmspec
Version: 0.19
Summary: Font packaging library in Fedora
Author-email: Fedora I18N team <i18n@lists.fedoraproject.org>
License-Expression: GPL-3.0-or-later
Project-URL: Homepage, https://github.com/fedora-i18n/font-rpm-spec-generator
Project-URL: Bug Tracker, https://github.com/fedora-i18n/font-rpm-spec-generator/issues
Keywords: fedora,fonts,packaging
Classifier: Development Status :: 4 - Beta
Classifier: Environment :: Console
Classifier: Operating System :: POSIX :: Linux
Classifier: Programming Language :: Python :: 3
Requires-Python: >=3.11
License-File: LICENSE
Requires-Dist: babel
Requires-Dist: fonttools
Requires-Dist: jinja2
Requires-Dist: lxml
Requires-Dist: python-rpm-spec>=0.12
Requires-Dist: termcolor
Dynamic: license-file
